odoo/addons/hr_holidays_public/README.rst
odoo/addons/hr_holidays_public/__init__.py
odoo/addons/hr_holidays_public/__manifest__.py
odoo/addons/hr_holidays_public/i18n/ar.po
odoo/addons/hr_holidays_public/i18n/ca.po
odoo/addons/hr_holidays_public/i18n/de.po
odoo/addons/hr_holidays_public/i18n/es.po
odoo/addons/hr_holidays_public/i18n/fi.po
odoo/addons/hr_holidays_public/i18n/fr.po
odoo/addons/hr_holidays_public/i18n/fr_FR.po
odoo/addons/hr_holidays_public/i18n/hr.po
odoo/addons/hr_holidays_public/i18n/hr_HR.po
odoo/addons/hr_holidays_public/i18n/hr_holidays_public.pot
odoo/addons/hr_holidays_public/i18n/it.po
odoo/addons/hr_holidays_public/i18n/nl_NL.po
odoo/addons/hr_holidays_public/i18n/pl.po
odoo/addons/hr_holidays_public/i18n/pt_BR.po
odoo/addons/hr_holidays_public/i18n/ro.po
odoo/addons/hr_holidays_public/i18n/sl.po
odoo/addons/hr_holidays_public/models/__init__.py
odoo/addons/hr_holidays_public/models/hr_employee.py
odoo/addons/hr_holidays_public/models/hr_leave.py
odoo/addons/hr_holidays_public/models/hr_leave_type.py
odoo/addons/hr_holidays_public/models/res_partner.py
odoo/addons/hr_holidays_public/models/res_users.py
odoo/addons/hr_holidays_public/models/resource_calendar.py
odoo/addons/hr_holidays_public/readme/CONFIGURE.md
odoo/addons/hr_holidays_public/readme/CONTRIBUTORS.md
odoo/addons/hr_holidays_public/readme/CREDITS.md
odoo/addons/hr_holidays_public/readme/DESCRIPTION.md
odoo/addons/hr_holidays_public/readme/ROADMAP.md
odoo/addons/hr_holidays_public/readme/USAGE.md
odoo/addons/hr_holidays_public/security/ir.model.access.csv
odoo/addons/hr_holidays_public/static/description/icon.png
odoo/addons/hr_holidays_public/static/description/icon.svg
odoo/addons/hr_holidays_public/static/description/index.html
odoo/addons/hr_holidays_public/tests/__init__.py
odoo/addons/hr_holidays_public/tests/test_holidays_calculation.py
odoo/addons/hr_holidays_public/tests/test_holidays_public.py
odoo/addons/hr_holidays_public/views/hr_leave_type.xml
odoo_addon_hr_holidays_public-18.0.1.0.5.dist-info/METADATA
odoo_addon_hr_holidays_public-18.0.1.0.5.dist-info/WHEEL
odoo_addon_hr_holidays_public-18.0.1.0.5.dist-info/top_level.txt
odoo_addon_hr_holidays_public-18.0.1.0.5.dist-info/RECORD
